Metadata-Version: 1.0
Name: marwan-hf-dist
Version: 0.1
Summary: marwan_hf_dist
Home-page: UNKNOWN
Author: UNKNOWN
Author-email: UNKNOWN
License: UNKNOWN
Platform: UNKNOWN
